{"ayahs": {"ayah_uthmani": "\u0642\u064f\u0644\u06e1 \u0628\u0650\u0641\u064e\u0636\u06e1\u0644\u0650 \u0671\u0644\u0644\u0651\u064e\u0647\u0650 \u0648\u064e\u0628\u0650\u0631\u064e\u062d\u06e1\u0645\u064e\u062a\u0650\u0647\u0650\u06e6 \u0641\u064e\u0628\u0650\u0630\u064e\u0670\u0644\u0650\u0643\u064e \u0641\u064e\u0644\u06e1\u064a\u064e\u0641\u06e1\u0631\u064e\u062d\u064f\u0648\u0627\u0652 \u0647\u064f\u0648\u064e \u062e\u064e\u064a\u06e1\u0631\u065e \u0645\u0651\u0650\u0645\u0651\u064e\u0627 \u064a\u064e\u062c\u06e1\u0645\u064e\u0639\u064f\u0648\u0646\u064e"}, "words": [{"word_arabic_uthmani": "\u0642\u064f\u0644\u06e1", "word_translation": "Say", "word_transliteration": "qul"}, {"word_arabic_uthmani": "\u0628\u0650\u0641\u064e\u0636\u06e1\u0644\u0650", "word_translation": "In the Bounty", "word_transliteration": "bifadli"}, {"word_arabic_uthmani": "\u0671\u0644\u0644\u0651\u064e\u0647\u0650", "word_translation": "(of) Allah", "word_transliteration": "al-lahi"}, {"word_arabic_uthmani": "\u0648\u064e\u0628\u0650\u0631\u064e\u062d\u06e1\u0645\u064e\u062a\u0650\u0647\u0650\u06e6", "word_translation": "and in His Mercy", "word_transliteration": "wabirahmatihi"}, {"word_arabic_uthmani": "\u0641\u064e\u0628\u0650\u0630\u064e\u0670\u0644\u0650\u0643\u064e", "word_translation": "so in that", "word_transliteration": "fabidhalika"}, {"word_arabic_uthmani": "\u0641\u064e\u0644\u06e1\u064a\u064e\u0641\u06e1\u0631\u064e\u062d\u064f\u0648\u0627\u0652", "word_translation": "let them rejoice", "word_transliteration": "falyafrahu"}, {"word_arabic_uthmani": "\u0647\u064f\u0648\u064e", "word_translation": "It", "word_transliteration": "huwa"}, {"word_arabic_uthmani": "\u062e\u064e\u064a\u06e1\u0631\u065e", "word_translation": "(is) better", "word_transliteration": "khayrun"}, {"word_arabic_uthmani": "\u0645\u0651\u0650\u0645\u0651\u064e\u0627", "word_translation": "than what", "word_transliteration": "mimma"}, {"word_arabic_uthmani": "\u064a\u064e\u062c\u06e1\u0645\u064e\u0639\u064f\u0648\u0646\u064e", "word_translation": "they accumulate", "word_transliteration": "yajma'una"}]}