{"ayahs": {"ayah_uthmani": "\u0648\u064e\u0645\u064e\u0627\u0653 \u0623\u064e\u0631\u06e1\u0633\u064e\u0644\u06e1\u0646\u064e\u0627 \u0645\u0650\u0646 \u0642\u064e\u0628\u06e1\u0644\u0650\u0643\u064e \u0625\u0650\u0644\u0651\u064e\u0627 \u0631\u0650\u062c\u064e\u0627\u0644\u0657\u0627 \u0646\u0651\u064f\u0648\u062d\u0650\u064a\u0653 \u0625\u0650\u0644\u064e\u064a\u06e1\u0647\u0650\u0645 \u0645\u0651\u0650\u0646\u06e1 \u0623\u064e\u0647\u06e1\u0644\u0650 \u0671\u0644\u06e1\u0642\u064f\u0631\u064e\u0649\u0670\u0653\u06d7 \u0623\u064e\u0641\u064e\u0644\u064e\u0645\u06e1 \u064a\u064e\u0633\u0650\u064a\u0631\u064f\u0648\u0627\u0652 \u0641\u0650\u064a \u0671\u0644\u06e1\u0623\u064e\u0631\u06e1\u0636\u0650 \u0641\u064e\u064a\u064e\u0646\u0638\u064f\u0631\u064f\u0648\u0627\u0652 \u0643\u064e\u064a\u06e1\u0641\u064e \u0643\u064e\u0627\u0646\u064e \u0639\u064e\u0670\u0642\u0650\u0628\u064e\u0629\u064f \u0671\u0644\u0651\u064e\u0630\u0650\u064a\u0646\u064e \u0645\u0650\u0646 \u0642\u064e\u0628\u06e1\u0644\u0650\u0647\u0650\u0645\u06e1\u06d7 \u0648\u064e\u0644\u064e\u062f\u064e\u0627\u0631\u064f \u0671\u0644\u06e1\u0623\u0653\u062e\u0650\u0631\u064e\u0629\u0650 \u062e\u064e\u064a\u06e1\u0631\u065e \u0644\u0651\u0650\u0644\u0651\u064e\u0630\u0650\u064a\u0646\u064e \u0671\u062a\u0651\u064e\u0642\u064e\u0648\u06e1\u0627\u0652\u06da \u0623\u064e\u0641\u064e\u0644\u064e\u0627 \u062a\u064e\u0639\u06e1\u0642\u0650\u0644\u064f\u0648\u0646\u064e"}, "words": [{"word_arabic_uthmani": "\u0648\u064e\u0645\u064e\u0627\u0653", "word_translation": "And not", "word_transliteration": "wama"}, {"word_arabic_uthmani": "\u0623\u064e\u0631\u06e1\u0633\u064e\u0644\u06e1\u0646\u064e\u0627", "word_translation": "We sent", "word_transliteration": "arsalna"}, {"word_arabic_uthmani": "\u0645\u0650\u0646", "word_translation": "before you", "word_transliteration": "min"}, {"word_arabic_uthmani": "\u0642\u064e\u0628\u06e1\u0644\u0650\u0643\u064e", "word_translation": "before you", "word_transliteration": "qablika"}, {"word_arabic_uthmani": "\u0625\u0650\u0644\u0651\u064e\u0627", "word_translation": "but", "word_transliteration": "illa"}, {"word_arabic_uthmani": "\u0631\u0650\u062c\u064e\u0627\u0644\u0657\u0627", "word_translation": "men", "word_transliteration": "rijalan"}, {"word_arabic_uthmani": "\u0646\u0651\u064f\u0648\u062d\u0650\u064a\u0653", "word_translation": "We revealed", "word_transliteration": "nuhi"}, {"word_arabic_uthmani": "\u0625\u0650\u0644\u064e\u064a\u06e1\u0647\u0650\u0645", "word_translation": "to them", "word_transliteration": "ilayhim"}, {"word_arabic_uthmani": "\u0645\u0651\u0650\u0646\u06e1", "word_translation": "from (among)", "word_transliteration": "min"}, {"word_arabic_uthmani": "\u0623\u064e\u0647\u06e1\u0644\u0650", "word_translation": "(the) people", "word_transliteration": "ahli"}, {"word_arabic_uthmani": "\u0671\u0644\u06e1\u0642\u064f\u0631\u064e\u0649\u0670\u0653\u06d7", "word_translation": "(of) the townships", "word_transliteration": "al-qura"}, {"word_arabic_uthmani": "\u0623\u064e\u0641\u064e\u0644\u064e\u0645\u06e1", "word_translation": "So have not", "word_transliteration": "afalam"}, {"word_arabic_uthmani": "\u064a\u064e\u0633\u0650\u064a\u0631\u064f\u0648\u0627\u0652", "word_translation": "they traveled", "word_transliteration": "yasiru"}, {"word_arabic_uthmani": "\u0641\u0650\u064a", "word_translation": "in", "word_transliteration": "fi"}, {"word_arabic_uthmani": "\u0671\u0644\u06e1\u0623\u064e\u0631\u06e1\u0636\u0650", "word_translation": "the earth", "word_transliteration": "al-ardi"}, {"word_arabic_uthmani": "\u0641\u064e\u064a\u064e\u0646\u0638\u064f\u0631\u064f\u0648\u0627\u0652", "word_translation": "and seen", "word_transliteration": "fayanzuru"}, {"word_arabic_uthmani": "\u0643\u064e\u064a\u06e1\u0641\u064e", "word_translation": "how", "word_transliteration": "kayfa"}, {"word_arabic_uthmani": "\u0643\u064e\u0627\u0646\u064e", "word_translation": "was", "word_transliteration": "kana"}, {"word_arabic_uthmani": "\u0639\u064e\u0670\u0642\u0650\u0628\u064e\u0629\u064f", "word_translation": "(the) end", "word_transliteration": "aqibatu"}, {"word_arabic_uthmani": "\u0671\u0644\u0651\u064e\u0630\u0650\u064a\u0646\u064e", "word_translation": "(of) those who", "word_transliteration": "alladhina"}, {"word_arabic_uthmani": "\u0645\u0650\u0646", "word_translation": "(were) before them", "word_transliteration": "min"}, {"word_arabic_uthmani": "\u0642\u064e\u0628\u06e1\u0644\u0650\u0647\u0650\u0645\u06e1\u06d7", "word_translation": "(were) before them", "word_transliteration": "qablihim"}, {"word_arabic_uthmani": "\u0648\u064e\u0644\u064e\u062f\u064e\u0627\u0631\u064f", "word_translation": "And surely the home", "word_transliteration": "waladaru"}, {"word_arabic_uthmani": "\u0671\u0644\u06e1\u0623\u0653\u062e\u0650\u0631\u064e\u0629\u0650", "word_translation": "(of) the Hereafter", "word_transliteration": "al-akhirati"}, {"word_arabic_uthmani": "\u062e\u064e\u064a\u06e1\u0631\u065e", "word_translation": "(is) best", "word_transliteration": "khayrun"}, {"word_arabic_uthmani": "\u0644\u0651\u0650\u0644\u0651\u064e\u0630\u0650\u064a\u0646\u064e", "word_translation": "for those who", "word_transliteration": "lilladhina"}, {"word_arabic_uthmani": "\u0671\u062a\u0651\u064e\u0642\u064e\u0648\u06e1\u0627\u0652\u06da", "word_translation": "fear Allah", "word_transliteration": "ittaqaw"}, {"word_arabic_uthmani": "\u0623\u064e\u0641\u064e\u0644\u064e\u0627", "word_translation": "Then will not", "word_transliteration": "afala"}, {"word_arabic_uthmani": "\u062a\u064e\u0639\u06e1\u0642\u0650\u0644\u064f\u0648\u0646\u064e", "word_translation": "you use reason", "word_transliteration": "ta'qiluna"}]}