{"ayahs": {"ayah_uthmani": "\u0648\u064e\u0644\u064e\u0645\u0651\u064e\u0627 \u062f\u064e\u062e\u064e\u0644\u064f\u0648\u0627\u0652 \u0645\u0650\u0646\u06e1 \u062d\u064e\u064a\u06e1\u062b\u064f \u0623\u064e\u0645\u064e\u0631\u064e\u0647\u064f\u0645\u06e1 \u0623\u064e\u0628\u064f\u0648\u0647\u064f\u0645 \u0645\u0651\u064e\u0627 \u0643\u064e\u0627\u0646\u064e \u064a\u064f\u063a\u06e1\u0646\u0650\u064a \u0639\u064e\u0646\u06e1\u0647\u064f\u0645 \u0645\u0651\u0650\u0646\u064e \u0671\u0644\u0644\u0651\u064e\u0647\u0650 \u0645\u0650\u0646 \u0634\u064e\u064a\u06e1\u0621\u064d \u0625\u0650\u0644\u0651\u064e\u0627 \u062d\u064e\u0627\u062c\u064e\u0629\u0657 \u0641\u0650\u064a \u0646\u064e\u0641\u06e1\u0633\u0650 \u064a\u064e\u0639\u06e1\u0642\u064f\u0648\u0628\u064e \u0642\u064e\u0636\u064e\u0649\u0670\u0647\u064e\u0627\u06da \u0648\u064e\u0625\u0650\u0646\u0651\u064e\u0647\u064f\u06e5 \u0644\u064e\u0630\u064f\u0648 \u0639\u0650\u0644\u06e1\u0645\u0656 \u0644\u0651\u0650\u0645\u064e\u0627 \u0639\u064e\u0644\u0651\u064e\u0645\u06e1\u0646\u064e\u0670\u0647\u064f \u0648\u064e\u0644\u064e\u0670\u0643\u0650\u0646\u0651\u064e \u0623\u064e\u0643\u06e1\u062b\u064e\u0631\u064e \u0671\u0644\u0646\u0651\u064e\u0627\u0633\u0650 \u0644\u064e\u0627 \u064a\u064e\u0639\u06e1\u0644\u064e\u0645\u064f\u0648\u0646\u064e"}, "words": [{"word_arabic_uthmani": "\u0648\u064e\u0644\u064e\u0645\u0651\u064e\u0627", "word_translation": "And when", "word_transliteration": "walamma"}, {"word_arabic_uthmani": "\u062f\u064e\u062e\u064e\u0644\u064f\u0648\u0627\u0652", "word_translation": "they entered", "word_transliteration": "dakhalu"}, {"word_arabic_uthmani": "\u0645\u0650\u0646\u06e1", "word_translation": "from", "word_transliteration": "min"}, {"word_arabic_uthmani": "\u062d\u064e\u064a\u06e1\u062b\u064f", "word_translation": "where", "word_transliteration": "haythu"}, {"word_arabic_uthmani": "\u0623\u064e\u0645\u064e\u0631\u064e\u0647\u064f\u0645\u06e1", "word_translation": "ordered them", "word_transliteration": "amarahum"}, {"word_arabic_uthmani": "\u0623\u064e\u0628\u064f\u0648\u0647\u064f\u0645", "word_translation": "their father", "word_transliteration": "abuhum"}, {"word_arabic_uthmani": "\u0645\u0651\u064e\u0627", "word_translation": "not", "word_transliteration": "ma"}, {"word_arabic_uthmani": "\u0643\u064e\u0627\u0646\u064e", "word_translation": "it", "word_transliteration": "kana"}, {"word_arabic_uthmani": "\u064a\u064f\u063a\u06e1\u0646\u0650\u064a", "word_translation": "avail(ed)", "word_transliteration": "yugh'ni"}, {"word_arabic_uthmani": "\u0639\u064e\u0646\u06e1\u0647\u064f\u0645", "word_translation": "them", "word_transliteration": "anhum"}, {"word_arabic_uthmani": "\u0645\u0651\u0650\u0646\u064e", "word_translation": "against", "word_transliteration": "mina"}, {"word_arabic_uthmani": "\u0671\u0644\u0644\u0651\u064e\u0647\u0650", "word_translation": "Allah", "word_transliteration": "al-lahi"}, {"word_arabic_uthmani": "\u0645\u0650\u0646", "word_translation": "any", "word_transliteration": "min"}, {"word_arabic_uthmani": "\u0634\u064e\u064a\u06e1\u0621\u064d", "word_translation": "thing", "word_transliteration": "shayin"}, {"word_arabic_uthmani": "\u0625\u0650\u0644\u0651\u064e\u0627", "word_translation": "but", "word_transliteration": "illa"}, {"word_arabic_uthmani": "\u062d\u064e\u0627\u062c\u064e\u0629\u0657", "word_translation": "(it was) a need", "word_transliteration": "hajatan"}, {"word_arabic_uthmani": "\u0641\u0650\u064a", "word_translation": "of", "word_transliteration": "fi"}, {"word_arabic_uthmani": "\u0646\u064e\u0641\u06e1\u0633\u0650", "word_translation": "(Yaqub's) soul", "word_transliteration": "nafsi"}, {"word_arabic_uthmani": "\u064a\u064e\u0639\u06e1\u0642\u064f\u0648\u0628\u064e", "word_translation": "Yaqub's (soul)", "word_transliteration": "ya'quba"}, {"word_arabic_uthmani": "\u0642\u064e\u0636\u064e\u0649\u0670\u0647\u064e\u0627\u06da", "word_translation": "which he carried out", "word_transliteration": "qadaha"}, {"word_arabic_uthmani": "\u0648\u064e\u0625\u0650\u0646\u0651\u064e\u0647\u064f\u06e5", "word_translation": "And indeed, he", "word_transliteration": "wa-innahu"}, {"word_arabic_uthmani": "\u0644\u064e\u0630\u064f\u0648", "word_translation": "(was) a possessor", "word_transliteration": "ladhu"}, {"word_arabic_uthmani": "\u0639\u0650\u0644\u06e1\u0645\u0656", "word_translation": "(of) knowledge", "word_transliteration": "il'min"}, {"word_arabic_uthmani": "\u0644\u0651\u0650\u0645\u064e\u0627", "word_translation": "because", "word_transliteration": "lima"}, {"word_arabic_uthmani": "\u0639\u064e\u0644\u0651\u064e\u0645\u06e1\u0646\u064e\u0670\u0647\u064f", "word_translation": "We had taught him", "word_transliteration": "allamnahu"}, {"word_arabic_uthmani": "\u0648\u064e\u0644\u064e\u0670\u0643\u0650\u0646\u0651\u064e", "word_translation": "but", "word_transliteration": "walakinna"}, {"word_arabic_uthmani": "\u0623\u064e\u0643\u06e1\u062b\u064e\u0631\u064e", "word_translation": "most", "word_transliteration": "akthara"}, {"word_arabic_uthmani": "\u0671\u0644\u0646\u0651\u064e\u0627\u0633\u0650", "word_translation": "(of) the people", "word_transliteration": "al-nasi"}, {"word_arabic_uthmani": "\u0644\u064e\u0627", "word_translation": "(do) not", "word_transliteration": "la"}, {"word_arabic_uthmani": "\u064a\u064e\u0639\u06e1\u0644\u064e\u0645\u064f\u0648\u0646\u064e", "word_translation": "know", "word_transliteration": "ya'lamuna"}]}