{"ayahs": {"ayah_uthmani": "\u0642\u064f\u0644\u06e1 \u0643\u064f\u0644\u0651\u065e \u064a\u064e\u0639\u06e1\u0645\u064e\u0644\u064f \u0639\u064e\u0644\u064e\u0649\u0670 \u0634\u064e\u0627\u0643\u0650\u0644\u064e\u062a\u0650\u0647\u0650\u06e6 \u0641\u064e\u0631\u064e\u0628\u0651\u064f\u0643\u064f\u0645\u06e1 \u0623\u064e\u0639\u06e1\u0644\u064e\u0645\u064f \u0628\u0650\u0645\u064e\u0646\u06e1 \u0647\u064f\u0648\u064e \u0623\u064e\u0647\u06e1\u062f\u064e\u0649\u0670 \u0633\u064e\u0628\u0650\u064a\u0644\u0657\u0627"}, "words": [{"word_arabic_uthmani": "\u0642\u064f\u0644\u06e1", "word_translation": "Say", "word_transliteration": "qul"}, {"word_arabic_uthmani": "\u0643\u064f\u0644\u0651\u065e", "word_translation": "Each", "word_transliteration": "kullun"}, {"word_arabic_uthmani": "\u064a\u064e\u0639\u06e1\u0645\u064e\u0644\u064f", "word_translation": "works", "word_transliteration": "ya'malu"}, {"word_arabic_uthmani": "\u0639\u064e\u0644\u064e\u0649\u0670", "word_translation": "on", "word_transliteration": "ala"}, {"word_arabic_uthmani": "\u0634\u064e\u0627\u0643\u0650\u0644\u064e\u062a\u0650\u0647\u0650\u06e6", "word_translation": "his manner", "word_transliteration": "shakilatihi"}, {"word_arabic_uthmani": "\u0641\u064e\u0631\u064e\u0628\u0651\u064f\u0643\u064f\u0645\u06e1", "word_translation": "but your Lord", "word_transliteration": "farabbukum"}, {"word_arabic_uthmani": "\u0623\u064e\u0639\u06e1\u0644\u064e\u0645\u064f", "word_translation": "(is) most knowing", "word_transliteration": "a'lamu"}, {"word_arabic_uthmani": "\u0628\u0650\u0645\u064e\u0646\u06e1", "word_translation": "of who", "word_transliteration": "biman"}, {"word_arabic_uthmani": "\u0647\u064f\u0648\u064e", "word_translation": "[he]", "word_transliteration": "huwa"}, {"word_arabic_uthmani": "\u0623\u064e\u0647\u06e1\u062f\u064e\u0649\u0670", "word_translation": "(is) best guided", "word_transliteration": "ahda"}, {"word_arabic_uthmani": "\u0633\u064e\u0628\u0650\u064a\u0644\u0657\u0627", "word_translation": "(in) way", "word_transliteration": "sabilan"}]}