{"ayahs": {"ayah_uthmani": "\u0641\u064e\u0633\u064e\u062e\u0651\u064e\u0631\u06e1\u0646\u064e\u0627 \u0644\u064e\u0647\u064f \u0671\u0644\u0631\u0651\u0650\u064a\u062d\u064e \u062a\u064e\u062c\u06e1\u0631\u0650\u064a \u0628\u0650\u0623\u064e\u0645\u06e1\u0631\u0650\u0647\u0650\u06e6 \u0631\u064f\u062e\u064e\u0627\u0653\u0621\u064b \u062d\u064e\u064a\u06e1\u062b\u064f \u0623\u064e\u0635\u064e\u0627\u0628\u064e"}, "words": [{"word_arabic_uthmani": "\u0641\u064e\u0633\u064e\u062e\u0651\u064e\u0631\u06e1\u0646\u064e\u0627", "word_translation": "Then We subjected", "word_transliteration": "fasakharna"}, {"word_arabic_uthmani": "\u0644\u064e\u0647\u064f", "word_translation": "to him", "word_transliteration": "lahu"}, {"word_arabic_uthmani": "\u0671\u0644\u0631\u0651\u0650\u064a\u062d\u064e", "word_translation": "the wind", "word_transliteration": "al-riha"}, {"word_arabic_uthmani": "\u062a\u064e\u062c\u06e1\u0631\u0650\u064a", "word_translation": "to flow", "word_transliteration": "tajri"}, {"word_arabic_uthmani": "\u0628\u0650\u0623\u064e\u0645\u06e1\u0631\u0650\u0647\u0650\u06e6", "word_translation": "by his command", "word_transliteration": "bi-amrihi"}, {"word_arabic_uthmani": "\u0631\u064f\u062e\u064e\u0627\u0653\u0621\u064b", "word_translation": "gently", "word_transliteration": "rukhaan"}, {"word_arabic_uthmani": "\u062d\u064e\u064a\u06e1\u062b\u064f", "word_translation": "wherever", "word_transliteration": "haythu"}, {"word_arabic_uthmani": "\u0623\u064e\u0635\u064e\u0627\u0628\u064e", "word_translation": "he directed", "word_transliteration": "asaba"}]}