{"ayahs": {"ayah_uthmani": "\u0633\u064e\u0644\u06e1\u0647\u064f\u0645\u06e1 \u0623\u064e\u064a\u0651\u064f\u0647\u064f\u0645 \u0628\u0650\u0630\u064e\u0670\u0644\u0650\u0643\u064e \u0632\u064e\u0639\u0650\u064a\u0645\u064c"}, "words": [{"word_arabic_uthmani": "\u0633\u064e\u0644\u06e1\u0647\u064f\u0645\u06e1", "word_translation": "Ask them", "word_transliteration": "salhum"}, {"word_arabic_uthmani": "\u0623\u064e\u064a\u0651\u064f\u0647\u064f\u0645", "word_translation": "which of them", "word_transliteration": "ayyuhum"}, {"word_arabic_uthmani": "\u0628\u0650\u0630\u064e\u0670\u0644\u0650\u0643\u064e", "word_translation": "for that", "word_transliteration": "bidhalika"}, {"word_arabic_uthmani": "\u0632\u064e\u0639\u0650\u064a\u0645\u064c", "word_translation": "(is) responsible", "word_transliteration": "za'imun"}]}