{"ayahs": {"ayah_uthmani": "\u062a\u064e\u062f\u06e1\u0639\u064f\u0648\u0627\u0652 \u0645\u064e\u0646\u06e1 \u0623\u064e\u062f\u06e1\u0628\u064e\u0631\u064e \u0648\u064e\u062a\u064e\u0648\u064e\u0644\u0651\u064e\u0649\u0670"}, "words": [{"word_arabic_uthmani": "\u062a\u064e\u062f\u06e1\u0639\u064f\u0648\u0627\u0652", "word_translation": "Inviting", "word_transliteration": "tad'u"}, {"word_arabic_uthmani": "\u0645\u064e\u0646\u06e1", "word_translation": "(him) who", "word_transliteration": "man"}, {"word_arabic_uthmani": "\u0623\u064e\u062f\u06e1\u0628\u064e\u0631\u064e", "word_translation": "turned his back", "word_transliteration": "adbara"}, {"word_arabic_uthmani": "\u0648\u064e\u062a\u064e\u0648\u064e\u0644\u0651\u064e\u0649\u0670", "word_translation": "and went away", "word_transliteration": "watawalla"}]}