{"ayahs": {"ayah_uthmani": "\u0648\u064e\u0645\u064e\u0627 \u0635\u064e\u0627\u062d\u0650\u0628\u064f\u0643\u064f\u0645 \u0628\u0650\u0645\u064e\u062c\u06e1\u0646\u064f\u0648\u0646\u0656"}, "words": [{"word_arabic_uthmani": "\u0648\u064e\u0645\u064e\u0627", "word_translation": "And not", "word_transliteration": "wama"}, {"word_arabic_uthmani": "\u0635\u064e\u0627\u062d\u0650\u0628\u064f\u0643\u064f\u0645", "word_translation": "(is) your companion", "word_transliteration": "sahibukum"}, {"word_arabic_uthmani": "\u0628\u0650\u0645\u064e\u062c\u06e1\u0646\u064f\u0648\u0646\u0656", "word_translation": "mad", "word_transliteration": "bimajnunin"}]}