{"ayahs": {"ayah_uthmani": "\u0625\u0650\u0646 \u062a\u064e\u0633\u06e1\u062a\u064e\u0641\u06e1\u062a\u0650\u062d\u064f\u0648\u0627\u0652 \u0641\u064e\u0642\u064e\u062f\u06e1 \u062c\u064e\u0627\u0653\u0621\u064e\u0643\u064f\u0645\u064f \u0671\u0644\u06e1\u0641\u064e\u062a\u06e1\u062d\u064f\u06d6 \u0648\u064e\u0625\u0650\u0646 \u062a\u064e\u0646\u062a\u064e\u0647\u064f\u0648\u0627\u0652 \u0641\u064e\u0647\u064f\u0648\u064e \u062e\u064e\u064a\u06e1\u0631\u065e \u0644\u0651\u064e\u0643\u064f\u0645\u06e1\u06d6 \u0648\u064e\u0625\u0650\u0646 \u062a\u064e\u0639\u064f\u0648\u062f\u064f\u0648\u0627\u0652 \u0646\u064e\u0639\u064f\u062f\u06e1 \u0648\u064e\u0644\u064e\u0646 \u062a\u064f\u063a\u06e1\u0646\u0650\u064a\u064e \u0639\u064e\u0646\u0643\u064f\u0645\u06e1 \u0641\u0650\u0626\u064e\u062a\u064f\u0643\u064f\u0645\u06e1 \u0634\u064e\u064a\u06e1\u0640\u0654\u0657\u0627 \u0648\u064e\u0644\u064e\u0648\u06e1 \u0643\u064e\u062b\u064f\u0631\u064e\u062a\u06e1 \u0648\u064e\u0623\u064e\u0646\u0651\u064e \u0671\u0644\u0644\u0651\u064e\u0647\u064e \u0645\u064e\u0639\u064e \u0671\u0644\u06e1\u0645\u064f\u0624\u06e1\u0645\u0650\u0646\u0650\u064a\u0646\u064e"}, "words": [{"word_arabic_uthmani": "\u0625\u0650\u0646", "word_translation": "If", "word_transliteration": "in"}, {"word_arabic_uthmani": "\u062a\u064e\u0633\u06e1\u062a\u064e\u0641\u06e1\u062a\u0650\u062d\u064f\u0648\u0627\u0652", "word_translation": "you ask for victory", "word_transliteration": "tastaftihu"}, {"word_arabic_uthmani": "\u0641\u064e\u0642\u064e\u062f\u06e1", "word_translation": "then certainly", "word_transliteration": "faqad"}, {"word_arabic_uthmani": "\u062c\u064e\u0627\u0653\u0621\u064e\u0643\u064f\u0645\u064f", "word_translation": "has come to you", "word_transliteration": "jaakumu"}, {"word_arabic_uthmani": "\u0671\u0644\u06e1\u0641\u064e\u062a\u06e1\u062d\u064f\u06d6", "word_translation": "the victory", "word_transliteration": "al-fathu"}, {"word_arabic_uthmani": "\u0648\u064e\u0625\u0650\u0646", "word_translation": "And if", "word_transliteration": "wa-in"}, {"word_arabic_uthmani": "\u062a\u064e\u0646\u062a\u064e\u0647\u064f\u0648\u0627\u0652", "word_translation": "you desist", "word_transliteration": "tantahu"}, {"word_arabic_uthmani": "\u0641\u064e\u0647\u064f\u0648\u064e", "word_translation": "then it (is)", "word_transliteration": "fahuwa"}, {"word_arabic_uthmani": "\u062e\u064e\u064a\u06e1\u0631\u065e", "word_translation": "good", "word_transliteration": "khayrun"}, {"word_arabic_uthmani": "\u0644\u0651\u064e\u0643\u064f\u0645\u06e1\u06d6", "word_translation": "for you", "word_transliteration": "lakum"}, {"word_arabic_uthmani": "\u0648\u064e\u0625\u0650\u0646", "word_translation": "but if", "word_transliteration": "wa-in"}, {"word_arabic_uthmani": "\u062a\u064e\u0639\u064f\u0648\u062f\u064f\u0648\u0627\u0652", "word_translation": "you return", "word_transliteration": "ta'udu"}, {"word_arabic_uthmani": "\u0646\u064e\u0639\u064f\u062f\u06e1", "word_translation": "We will return (too)", "word_transliteration": "na'ud"}, {"word_arabic_uthmani": "\u0648\u064e\u0644\u064e\u0646", "word_translation": "And never", "word_transliteration": "walan"}, {"word_arabic_uthmani": "\u062a\u064f\u063a\u06e1\u0646\u0650\u064a\u064e", "word_translation": "will avail", "word_transliteration": "tugh'niya"}, {"word_arabic_uthmani": "\u0639\u064e\u0646\u0643\u064f\u0645\u06e1", "word_translation": "you", "word_transliteration": "ankum"}, {"word_arabic_uthmani": "\u0641\u0650\u0626\u064e\u062a\u064f\u0643\u064f\u0645\u06e1", "word_translation": "your forces", "word_transliteration": "fi-atukum"}, {"word_arabic_uthmani": "\u0634\u064e\u064a\u06e1\u0640\u0654\u0657\u0627", "word_translation": "anything", "word_transliteration": "shayan"}, {"word_arabic_uthmani": "\u0648\u064e\u0644\u064e\u0648\u06e1", "word_translation": "even if", "word_transliteration": "walaw"}, {"word_arabic_uthmani": "\u0643\u064e\u062b\u064f\u0631\u064e\u062a\u06e1", "word_translation": "(they are) numerous", "word_transliteration": "kathurat"}, {"word_arabic_uthmani": "\u0648\u064e\u0623\u064e\u0646\u0651\u064e", "word_translation": "And that", "word_transliteration": "wa-anna"}, {"word_arabic_uthmani": "\u0671\u0644\u0644\u0651\u064e\u0647\u064e", "word_translation": "Allah", "word_transliteration": "al-laha"}, {"word_arabic_uthmani": "\u0645\u064e\u0639\u064e", "word_translation": "(is) with", "word_transliteration": "ma'a"}, {"word_arabic_uthmani": "\u0671\u0644\u06e1\u0645\u064f\u0624\u06e1\u0645\u0650\u0646\u0650\u064a\u0646\u064e", "word_translation": "the believers", "word_transliteration": "al-mu'minina"}]}