{"ayahs": {"ayah_uthmani": "\u0644\u064e\u0627 \u062a\u064e\u0639\u06e1\u062a\u064e\u0630\u0650\u0631\u064f\u0648\u0627\u0652 \u0642\u064e\u062f\u06e1 \u0643\u064e\u0641\u064e\u0631\u06e1\u062a\u064f\u0645 \u0628\u064e\u0639\u06e1\u062f\u064e \u0625\u0650\u064a\u0645\u064e\u0670\u0646\u0650\u0643\u064f\u0645\u06e1\u06da \u0625\u0650\u0646 \u0646\u0651\u064e\u0639\u06e1\u0641\u064f \u0639\u064e\u0646 \u0637\u064e\u0627\u0653\u0626\u0650\u0641\u064e\u0629\u0656 \u0645\u0651\u0650\u0646\u0643\u064f\u0645\u06e1 \u0646\u064f\u0639\u064e\u0630\u0651\u0650\u0628\u06e1 \u0637\u064e\u0627\u0653\u0626\u0650\u0641\u064e\u0629\u064e\u06e2 \u0628\u0650\u0623\u064e\u0646\u0651\u064e\u0647\u064f\u0645\u06e1 \u0643\u064e\u0627\u0646\u064f\u0648\u0627\u0652 \u0645\u064f\u062c\u06e1\u0631\u0650\u0645\u0650\u064a\u0646\u064e"}, "words": [{"word_arabic_uthmani": "\u0644\u064e\u0627", "word_translation": "(Do) not", "word_transliteration": "la"}, {"word_arabic_uthmani": "\u062a\u064e\u0639\u06e1\u062a\u064e\u0630\u0650\u0631\u064f\u0648\u0627\u0652", "word_translation": "make excuse", "word_transliteration": "ta'tadhiru"}, {"word_arabic_uthmani": "\u0642\u064e\u062f\u06e1", "word_translation": "verily", "word_transliteration": "qad"}, {"word_arabic_uthmani": "\u0643\u064e\u0641\u064e\u0631\u06e1\u062a\u064f\u0645", "word_translation": "you have disbelieved", "word_transliteration": "kafartum"}, {"word_arabic_uthmani": "\u0628\u064e\u0639\u06e1\u062f\u064e", "word_translation": "after", "word_transliteration": "ba'da"}, {"word_arabic_uthmani": "\u0625\u0650\u064a\u0645\u064e\u0670\u0646\u0650\u0643\u064f\u0645\u06e1\u06da", "word_translation": "your belief", "word_transliteration": "imanikum"}, {"word_arabic_uthmani": "\u0625\u0650\u0646", "word_translation": "If", "word_transliteration": "in"}, {"word_arabic_uthmani": "\u0646\u0651\u064e\u0639\u06e1\u0641\u064f", "word_translation": "We pardon", "word_transliteration": "na'fu"}, {"word_arabic_uthmani": "\u0639\u064e\u0646", "word_translation": "[on]", "word_transliteration": "an"}, {"word_arabic_uthmani": "\u0637\u064e\u0627\u0653\u0626\u0650\u0641\u064e\u0629\u0656", "word_translation": "a party", "word_transliteration": "taifatin"}, {"word_arabic_uthmani": "\u0645\u0651\u0650\u0646\u0643\u064f\u0645\u06e1", "word_translation": "of you", "word_transliteration": "minkum"}, {"word_arabic_uthmani": "\u0646\u064f\u0639\u064e\u0630\u0651\u0650\u0628\u06e1", "word_translation": "We will punish", "word_transliteration": "nu'adhib"}, {"word_arabic_uthmani": "\u0637\u064e\u0627\u0653\u0626\u0650\u0641\u064e\u0629\u064e\u06e2", "word_translation": "a party", "word_transliteration": "taifatan"}, {"word_arabic_uthmani": "\u0628\u0650\u0623\u064e\u0646\u0651\u064e\u0647\u064f\u0645\u06e1", "word_translation": "because they", "word_transliteration": "bi-annahum"}, {"word_arabic_uthmani": "\u0643\u064e\u0627\u0646\u064f\u0648\u0627\u0652", "word_translation": "were", "word_transliteration": "kanu"}, {"word_arabic_uthmani": "\u0645\u064f\u062c\u06e1\u0631\u0650\u0645\u0650\u064a\u0646\u064e", "word_translation": "criminals", "word_transliteration": "muj'rimina"}]}